{"dnpFFhSOtfUbHg4qh8EPiA==":"mbr-1920x1280.jpg","HQNwF1BHYWGCv/yfwpU62A==":"mbr-1-1920x1280.jpg","jUYGvLdLFwAMKyvpzpOgxg==":"mbr-596x398.jpg","lLgqmlv4e1t1lefnuuVShw==":"mbr-1200x800.jpg","ebP4IxfKDU8wJWWzwaKQsQ==":"mbr-1-1200x800.jpg","5lL+TKCrBvJzbmoZ6vwYCA==":"gcash-596x526.png","MoSJx9IFWVDdG9G3a5LApA==":"maya-596x336.jpg","ZYAKIWclFOlCHLM64OB+AA==":"lbp-596x283.png","ZKRM5GGuDcgBp0KZYrx6Xw==":"lbp-1-596x283.png","EVAc+dxF4PmkV7NjZQcNlQ==":"dbp-596x544.png","2gMmjs18fYDZSXODbwTTzA==":"business%20permit-812x794.png","QRrToLEPjEdduFHm7QGvjg==":"rp-1036x1101.png","ed+c0nv31XuILQ/3+Swtzg==":"rp-1036x1178.png","bOEr4Kp8xMELWjXk3VdFIw==":"appointment-1036x1024.png","J5A2JOGg1/aEpGjkVxvldw==":"gov-1080x145.jpg","yKFr4TamkT+/HurFM0lyow==":"html-120x120.png","KPu5+byD+h0paNzzA3GLRQ==":"html-1-120x120.png","V3mlRF92Tu5xry07vdqVTA==":"css-85x120.png","BII6M8PdT4qp26Y1bTrLgw==":"js-111x120.png","m28VJT8wgZND4o3uskQNpw==":"asp-178x135.png","5O8SES4RCV9QsiLAmTi99Q==":"vb-131x130.png","9B06zwF6yF8oGV3Icx9YGw==":"mssql-148x148.png","nPUySalnMqQz1A7Pi3pMAg==":"html-120x149.png","tv9Jq6qOVvBbM7QOriOjLQ==":"css-85x106.png","7t0KxY6ouhyohN2SbpbAdg==":"js-111x138.png","0mSCLF6Pa0V0r6Sz7wjqYw==":"asp-178x222.png","T84q0ZJ93jKasc4wGCP5uA==":"vb-131x163.png","yIYdZX3IlYTwBGjmOfGm8A==":"mssql-148x184.png","CIDEWpimNY71WcAWh+wWEw==":"html-120x173.png","uDy/fGVta6fc5zD6chrcog==":"css-85x123.png","f3QhtXq5AoZRCEw4TZJiDg==":"js-111x160.png","QfVRwJ3QhIVDfNppoNS1Sg==":"asp-178x257.png","5wDqhmcjO4sx6KuAZJP1tg==":"vb-131x189.png","GtLmRs7B9twkP8LDbI+7ig==":"mssql-148x214.png","dx++Lk+Zvbem1Uxi4T0pzw==":"picture1-724x1120.jpg","wYcdKWRmegGqLh202ktoyg==":"a-1280x960.jpg","EtgJheYmsaHTlIbb00dWQA==":"a-1280x960.jpeg"}